sphinxcontrib_gravatar-0.1.2-py2.7-nspkg.pth
sphinxcontrib/gravatar/__init__.py
sphinxcontrib/gravatar/compat.py
sphinxcontrib/gravatar/directives.py
sphinxcontrib/gravatar/nodes.py
sphinxcontrib_gravatar-0.1.2.dist-info/DESCRIPTION.rst
sphinxcontrib_gravatar-0.1.2.dist-info/METADATA
sphinxcontrib_gravatar-0.1.2.dist-info/metadata.json
sphinxcontrib_gravatar-0.1.2.dist-info/namespace_packages.txt
sphinxcontrib_gravatar-0.1.2.dist-info/RECORD
sphinxcontrib_gravatar-0.1.2.dist-info/top_level.txt
sphinxcontrib_gravatar-0.1.2.dist-info/WHEEL
