Metadata-Version: 2.0
Name: sphinxcontrib-gravatar
Version: 0.1.2
Summary: Sphinx "gravatar" extension
Home-page: https://github.com/tell-k/sphinxcontrib-gravatar
Author: tell-k
Author-email: ffk2005 at gmail.com
License: BSD
Download-URL: http://pypi.python.org/pypi/sphinxcontrib-gravatar
Platform: any
Classifier: Development Status :: 4 - Beta
Classifier: Environment :: Console
Classifier: Environment :: Web Environment
Classifier: Intended Audience :: Developers
Classifier: License :: OSI Approved :: BSD License
Classifier: Operating System :: OS Independent
Classifier: Programming Language :: Python :: 2
Classifier: Programming Language :: Python :: 2.6
Classifier: Programming Language :: Python :: 2.7
Classifier: Programming Language :: Python :: 3
Classifier: Programming Language :: Python :: 3.3
Classifier: Programming Language :: Python :: 3.4
Classifier: Topic :: Documentation
Classifier: Topic :: Utilities
Requires-Dist: Sphinx (>=1.2)
